pptx_to_html5/__init__.py
pptx_to_html5/cli.py
pptx_to_html5/converter.py
pptx_to_html5/templates/presentation.html
pptx_to_html5/templates/script.js
pptx_to_html5/templates/styles.css
pptx_to_html5-0.1.0.dist-info/licenses/LICENSE
pptx_to_html5-0.1.0.dist-info/METADATA
pptx_to_html5-0.1.0.dist-info/WHEEL
pptx_to_html5-0.1.0.dist-info/entry_points.txt
pptx_to_html5-0.1.0.dist-info/top_level.txt
pptx_to_html5-0.1.0.dist-info/RECORD
