Metadata-Version: 2.4
Name: pptx-to-html5
Version: 0.1.0
Summary: Tools for converting PowerPoint presentations to HTML5 websites
Author: pptx-to-html5 contributors
License: Unlicense
Classifier: Development Status :: 3 - Alpha
Classifier: Intended Audience :: Developers
Classifier: License :: OSI Approved :: The Unlicense (Unlicense)
Classifier: Programming Language :: Python :: 3
Classifier: Programming Language :: Python :: 3.12
Classifier: Programming Language :: Python :: 3.13
Requires-Python: >=3.12
License-File: LICENSE
Requires-Dist: python-pptx>=0.6.21
Requires-Dist: Pillow>=10.2.0
Requires-Dist: Jinja2>=3.1.0
Provides-Extra: dev
Requires-Dist: pytest>=7.4.0; extra == "dev"
Requires-Dist: pytest-cov>=4.1.0; extra == "dev"
Requires-Dist: ruff>=0.1.0; extra == "dev"
Requires-Dist: mypy>=1.5.0; extra == "dev"
Dynamic: license-file
